bcx/__init__.py
bcx/channels.py
bcx/client.py
bcx/manager.py
bcx/orders.py
bcx/utils.py
bcx/websocket.py
bcx-0.2.1.dist-info/LICENSE
bcx-0.2.1.dist-info/METADATA
bcx-0.2.1.dist-info/WHEEL
bcx-0.2.1.dist-info/top_level.txt
bcx-0.2.1.dist-info/RECORD
